srttranslatelocal/__init__.py
srttranslatelocal/srttranslate.py
srttranslatelocal/srttranslatemain.py
srttranslatelocal/utilities.py
srttranslatelocal-0.6.0.dist-info/METADATA
srttranslatelocal-0.6.0.dist-info/WHEEL
srttranslatelocal-0.6.0.dist-info/entry_points.txt
srttranslatelocal-0.6.0.dist-info/top_level.txt
srttranslatelocal-0.6.0.dist-info/RECORD
