Metadata-Version: 2.1
Name: srttranslatelocal
Version: 0.6.0
Summary: Translate SRT Locally Using Argos Translate
Author: codexhound
License: MIT License
Project-URL: Homepage, https://github.com/codexhound/srttranslatelocal
Project-URL: Issues, https://github.com/codexhound/srttranslatelocal/issues
Keywords: translation,subtitles,srt,plex
Classifier: Programming Language :: Python :: 3
Classifier: License :: OSI Approved :: MIT License
Classifier: Operating System :: OS Independent
Requires-Python: >=3.8
Requires-Dist: translatehtml
Requires-Dist: argostranslate
